draftretriever-0.1.1.dist-info/METADATA
draftretriever-0.1.1.dist-info/WHEEL
draftretriever/py.typed
draftretriever/__init__.py
draftretriever/draftretriever.pyi
draftretriever/draftretriever.cpython-311-x86_64-linux-gnu.so
draftretriever-0.1.1.dist-info/RECORD
