Metadata-Version: 2.3
Name: draftretriever
Version: 0.1.1
